simplest_async_s3client/__init__.py
simplest_async_s3client/s3client.py
simplest_async_s3client-0.0.6.dist-info/licenses/LICENSE
simplest_async_s3client-0.0.6.dist-info/METADATA
simplest_async_s3client-0.0.6.dist-info/WHEEL
simplest_async_s3client-0.0.6.dist-info/top_level.txt
simplest_async_s3client-0.0.6.dist-info/RECORD
