Metadata-Version: 2.4
Name: simplest_async_s3client
Version: 0.0.6
Summary: A simple async client for aws s3 storage
Author-email: Aleksandr Berezhnoy <aberezhnoy1980@gmail.com>
License-Expression: MIT
Project-URL: Homepage, https://github.com/Aberezhnoy1980/MarketGenius/tree/main/ds_app/src/clients/s3_client
Project-URL: Issues, https://github.com/Aberezhnoy1980/MarketGenius/issues
Classifier: Programming Language :: Python :: 3
Classifier: Operating System :: OS Independent
Requires-Python: >=3.9
License-File: LICENSE
Requires-Dist: aiobotocore
Dynamic: license-file
